ip2region/__init__.py
ip2region/searcher.py
ip2region/util.py
py_ip2region-3.0.2.dist-info/licenses/LICENSE
py_ip2region-3.0.2.dist-info/METADATA
py_ip2region-3.0.2.dist-info/WHEEL
py_ip2region-3.0.2.dist-info/top_level.txt
py_ip2region-3.0.2.dist-info/RECORD
