Metadata-Version: 2.4
Name: py-ip2region
Version: 3.0.2
Summary: ip2region official python binding with both IPv4 and IPv6 supported
Home-page: https://github.com/lionsoul2014/ip2region
Author: lionsoul2014
Author-email: chenxin619315@gmail.com
License: Apache-2.0 License
Keywords: ip2region,ip-address,ip-region,ip-location,ip-lookup,ip-search,ipv4-address,ipv4-region,ipv4-location,ipv4-lookup,ipv4-search,ipv6-address,ipv6-region,ipv6-location,ipv6-lookup,ipv6-search
Classifier: Programming Language :: Python :: 3
Classifier: Operating System :: OS Independent
License-File: LICENSE
Dynamic: author
Dynamic: author-email
Dynamic: classifier
Dynamic: description
Dynamic: description-content-type
Dynamic: home-page
Dynamic: keywords
Dynamic: license
Dynamic: license-file
Dynamic: summary
